ww/b.py
ww/s.py
ww/t.py
ww/d.py
ww/g.py
ww/p.py
ww/iterable.py
ww/__init__.py
ww/types.py
ww/utils.py
ww/wrappers/__init__.py
ww/wrappers/bytes.py
ww/wrappers/objects.py
ww/wrappers/paths.py
ww/wrappers/base.py
ww/wrappers/dicts.py
ww/wrappers/iterables.py
ww/wrappers/lists.py
ww/wrappers/strings.py
ww/wrappers/tuples.py
ww/tools/__init__.py
ww/tools/iterables.py
ww/tools/strings.py
ww-0.2.1.dist-info/top_level.txt
ww-0.2.1.dist-info/METADATA
ww-0.2.1.dist-info/DESCRIPTION.rst
ww-0.2.1.dist-info/metadata.json
ww-0.2.1.dist-info/WHEEL
ww-0.2.1.dist-info/RECORD
