Metadata-Version: 1.1
Name: ww
Version: 0.2.1
Summary: Wrappers for Python builtins with higher-level APIs
Home-page: https://github.com/tygs/ww/
Author: Sam et Max
Author-email: lesametlemax@gmail.com
License: MIT
Keywords: ww
Platform: UNKNOWN
Classifier: Development Status :: 1 - Planning
Classifier: Intended Audience :: Developers
Classifier: Natural Language :: English
Classifier: Programming Language :: Python :: 2.7
Classifier: Programming Language :: Python :: 3.3
Classifier: Programming Language :: Python :: 3.4
Classifier: Programming Language :: Python :: 3.5
Classifier: Operating System :: OS Independent
